{
  "data": {
    "_serverScript": [
      {
        "path": "server/bowling"
      }
    ],
    "actorName": {
      "asset": "asset/map_tron_tim/b7s.actor"
    },
    "AI_attack": {
      "enable": true
    },
    "AI_patrol": {
      "patrolMode": "randomPath"
    },
    "canClick": true,
    "collision": true,
    "girlactor": {
      "asset": "asset/map_tron_tim/b7s.actor"
    },
    "hideName": true,
    "name": {
      "value": "e4ae9127-5c87-464a-afe3-12f09b1ae3ae"
    }
  },
  "meta": {
    "EXPORT": {
      "setting.json": "ec2e9daa75cdd73145edbfc25edd455e",
      "triggers.bts": ""
    },
    "VERSION": "0.21"
  }
}